whiteprints_template_context/__init__.py
whiteprints_template_context/context.py
whiteprints_template_context/filters.py
whiteprints_template_context/loc.py
whiteprints_template_context/package_metadata.py
whiteprints_template_context/py.typed
whiteprints_template_context-0.6.0.dist-info/METADATA
whiteprints_template_context-0.6.0.dist-info/WHEEL
whiteprints_template_context-0.6.0.dist-info/licenses/LICENSES/CC-BY-NC-SA-4.0.txt
whiteprints_template_context-0.6.0.dist-info/licenses/LICENSES/MIT.txt
whiteprints_template_context-0.6.0.dist-info/RECORD
