Metadata-Version: 2.4
Name: whiteprints-template-context
Version: 0.6.0
Summary: Interpolate variables and set Copier Jinja context
Project-URL: changelog, https://github.com/whiteprints/whiteprints-template-context/releases
Project-URL: discussions, https://github.com/whiteprints/whiteprints-template-context/discussions
Project-URL: documentation, https://github.com/whiteprints/whiteprints-template-context
Project-URL: download, https://github.com/whiteprints/whiteprints-template-context/releases
Project-URL: homepage, https://github.com/whiteprints/whiteprints-template-context
Project-URL: integration, https://github.com/whiteprints/whiteprints-template-context/actions
Project-URL: issues, https://github.com/whiteprints/whiteprints-template-context/issues
Project-URL: pypi, https://pypi.org/project/whiteprints-template-context
Project-URL: repository, https://github.com/whiteprints/whiteprints-template-context
Author: Romain Brault
Maintainer: Romain Brault
License-Expression: MIT
License-File: LICENSES/CC-BY-NC-SA-4.0.txt
License-File: LICENSES/MIT.txt
Keywords: Python
Classifier: Development Status :: 1 - Planning
Classifier: Environment :: Console
Classifier: Framework :: Pytest
Classifier: Framework :: Sphinx
Classifier: Framework :: tox
Classifier: Intended Audience :: Developers
Classifier: Natural Language :: English
Classifier: Operating System :: OS Independent
Classifier: Programming Language :: Python
Classifier: Programming Language :: Python :: 3 :: Only
Classifier: Programming Language :: Python :: 3.9
Classifier: Programming Language :: Python :: 3.10
Classifier: Programming Language :: Python :: 3.11
Classifier: Programming Language :: Python :: 3.12
Classifier: Programming Language :: Python :: 3.13
Classifier: Typing :: Typed
Requires-Python: <4.0,>=3.9
Requires-Dist: copier-templates-extensions>=0.3
Requires-Dist: jinja2-time>=0.2
Requires-Dist: license-expression>=30.3.1
Requires-Dist: typing-extensions>=4.12.2; python_full_version < '3.12'
